simwave/__init__.py
simwave/_version.py
simwave/io/__init__.py
simwave/io/io.py
simwave/kernel/__init__.py
simwave/kernel/backend/__init__.py
simwave/kernel/backend/compiler.py
simwave/kernel/backend/middleware.py
simwave/kernel/backend/c_code/forward/constant_density/2d/wave.c
simwave/kernel/backend/c_code/forward/constant_density/3d/wave.c
simwave/kernel/backend/c_code/forward/variable_density/2d/wave.c
simwave/kernel/backend/c_code/forward/variable_density/3d/wave.c
simwave/kernel/frontend/__init__.py
simwave/kernel/frontend/fd.py
simwave/kernel/frontend/kws.py
simwave/kernel/frontend/model.py
simwave/kernel/frontend/solver.py
simwave/kernel/frontend/source.py
simwave/plots/__init__.py
simwave/plots/plot.py
simwave-1.0.dist-info/LICENSE
simwave-1.0.dist-info/METADATA
simwave-1.0.dist-info/WHEEL
simwave-1.0.dist-info/top_level.txt
simwave-1.0.dist-info/RECORD
