Metadata-Version: 2.1
Name: simwave
Version: 1.0
Summary: Finite difference 2D/3D acoustic wave propagator.
Home-page: https://github.com/HPCSys-Lab/simwave
Author: HPCSys-Lab
Author-email: senger.hermes@gmail.com
License: GPL-3.0 License
Platform: UNKNOWN
Classifier: Development Status :: 4 - Beta
Classifier: Intended Audience :: Developers
Classifier: Intended Audience :: Science/Research
Classifier: Topic :: Scientific/Engineering :: Mathematics
Classifier: Topic :: Scientific/Engineering :: Physics
Classifier: License :: OSI Approved :: GNU General Public License v3 (GPLv3)
Classifier: Programming Language :: Python :: 3
Classifier: Programming Language :: Python :: 3.6
Classifier: Programming Language :: Python :: 3.7
Classifier: Programming Language :: Python :: 3.8
Classifier: Programming Language :: Python :: 3.9
License-File: LICENSE
Requires-Dist: numpy (>=1.18.1)
Requires-Dist: matplotlib (>=3.2.1)
Requires-Dist: segyio (>=1.9.1)
Requires-Dist: scipy (>=1.4.1)
Requires-Dist: pytest (>=6.2.2)
Requires-Dist: findiff (>=0.8.9)
Requires-Dist: pytest-codeblocks (>=0.10.4)
